cellpose_omni/__init__.py
cellpose_omni/__main__.py
cellpose_omni/core.py
cellpose_omni/dynamics.py
cellpose_omni/io.py
cellpose_omni/metrics.py
cellpose_omni/models.py
cellpose_omni/plot.py
cellpose_omni/resnet_style.py
cellpose_omni/resnet_torch.py
cellpose_omni/test_mkl.py
cellpose_omni/transforms.py
cellpose_omni/utils.py
cellpose_omni/gui/__init__.py
cellpose_omni/gui/gui.py
cellpose_omni/gui/guiparts.py
cellpose_omni/gui/guiutils.py
cellpose_omni/gui/io.py
cellpose_omni/gui/menus.py
cellpose_omni/gui/qt.conf
cellpose_omni/gui/MainWindowModules/__init__.py
cellpose_omni/gui/MainWindowModules/annotation.py
cellpose_omni/gui/MainWindowModules/brush.py
cellpose_omni/gui/MainWindowModules/buttons.py
cellpose_omni/gui/MainWindowModules/crosshairs.py
cellpose_omni/gui/MainWindowModules/cursor.py
cellpose_omni/gui/MainWindowModules/files.py
cellpose_omni/gui/MainWindowModules/image.py
cellpose_omni/gui/MainWindowModules/keypress.py
cellpose_omni/gui/MainWindowModules/logger.py
cellpose_omni/gui/MainWindowModules/models.py
cellpose_omni/gui/MainWindowModules/ortho.py
cellpose_omni/gui/MainWindowModules/saving.py
cellpose_omni/gui/MainWindowModules/seg.py
cellpose_omni/gui/MainWindowModules/settings.py
cellpose_omni/gui/MainWindowModules/theme.py
cellpose_omni/gui/MainWindowModules/update.py
cellpose_omni/gui/assets/__init__.py
cellpose_omni/gui/assets/brush.svg
cellpose_omni/gui/assets/gamma.svg
cellpose_omni/gui/assets/logo.png
cellpose_omni/logo/cellpose.ico
cellpose_omni/logo/logo.png
omnipose/__init__.py
omnipose/__main__.py
omnipose/cli.py
omnipose/color.py
omnipose/core.py
omnipose/data.py
omnipose/dependencies.py
omnipose/gpu.py
omnipose/logger.py
omnipose/loss.py
omnipose/measure.py
omnipose/misc.py
omnipose/plot.py
omnipose/profiling.py
omnipose/stacks.py
omnipose/transforms.py
omnipose/utils copy.py
omnipose/utils.py
omnipose-1.1.4.dist-info/licenses/LICENSE
omnipose-1.1.4.dist-info/METADATA
omnipose-1.1.4.dist-info/WHEEL
omnipose-1.1.4.dist-info/entry_points.txt
omnipose-1.1.4.dist-info/top_level.txt
omnipose-1.1.4.dist-info/RECORD
