Metadata-Version: 2.4
Name: omnipose
Version: 1.1.4
Summary: cell segmentation algorithm improving on the Cellpose framework
Home-page: https://github.com/kevinjohncutler/omnipose
Author: Kevin Cutler
Author-email: kevinjohncutler@outlook.com
Classifier: Programming Language :: Python :: 3
Classifier: Operating System :: OS Independent
License-File: LICENSE
Requires-Dist: numba>=0.61.0
Requires-Dist: numpy
Requires-Dist: scipy
Requires-Dist: edt
Requires-Dist: scikit-image
Requires-Dist: ncolor>=1.4.3
Requires-Dist: scikit-learn
Requires-Dist: torch>=1.10
Requires-Dist: torchvision
Requires-Dist: mahotas>=1.4.13
Requires-Dist: mgen
Requires-Dist: matplotlib
Requires-Dist: ipywidgets
Requires-Dist: networkit
Requires-Dist: torchvf
Requires-Dist: tqdm
Requires-Dist: natsort
Requires-Dist: aicsimageio
Requires-Dist: numexpr
Requires-Dist: torch_optimizer
Requires-Dist: tifffile
Requires-Dist: fastremap
Requires-Dist: cmap
Requires-Dist: colour-science
Requires-Dist: dbscan
Requires-Dist: pyinstrument
Requires-Dist: imagecodecs
Requires-Dist: opencv-python-headless
Requires-Dist: opt_einsum
Requires-Dist: dask
Requires-Dist: dask-image
Requires-Dist: scikit-learn
Provides-Extra: gui
Requires-Dist: pyqtgraph>=0.12.4; extra == "gui"
Requires-Dist: PyQt6; extra == "gui"
Requires-Dist: omnipose-theme; extra == "gui"
Requires-Dist: superqt; extra == "gui"
Requires-Dist: darkdetect; extra == "gui"
Requires-Dist: qtawesome; extra == "gui"
Requires-Dist: pyopengl; extra == "gui"
Requires-Dist: imageio; extra == "gui"
Provides-Extra: docs
Requires-Dist: sphinx_copybutton; extra == "docs"
Requires-Dist: sphinx_automodapi; extra == "docs"
Requires-Dist: sphinx_design; extra == "docs"
Requires-Dist: sphinx-argparse; extra == "docs"
Requires-Dist: myst_nb>=1.2; extra == "docs"
Requires-Dist: furo; extra == "docs"
Requires-Dist: sphinx>=8; extra == "docs"
Requires-Dist: sphinx-rtd-theme>=3; extra == "docs"
Requires-Dist: sphinx-autodoc-typehints>=3; extra == "docs"
Requires-Dist: matplotlib; extra == "docs"
Requires-Dist: numpy; extra == "docs"
Provides-Extra: all
Requires-Dist: sphinx_copybutton; extra == "all"
Requires-Dist: sphinx_automodapi; extra == "all"
Requires-Dist: sphinx_design; extra == "all"
Requires-Dist: sphinx-argparse; extra == "all"
Requires-Dist: myst_nb>=1.2; extra == "all"
Requires-Dist: furo; extra == "all"
Requires-Dist: sphinx>=8; extra == "all"
Requires-Dist: sphinx-rtd-theme>=3; extra == "all"
Requires-Dist: sphinx-autodoc-typehints>=3; extra == "all"
Requires-Dist: matplotlib; extra == "all"
Requires-Dist: numpy; extra == "all"
Requires-Dist: pyqtgraph>=0.12.4; extra == "all"
Requires-Dist: PyQt6; extra == "all"
Requires-Dist: omnipose-theme; extra == "all"
Requires-Dist: superqt; extra == "all"
Requires-Dist: darkdetect; extra == "all"
Requires-Dist: qtawesome; extra == "all"
Requires-Dist: pyopengl; extra == "all"
Requires-Dist: imageio; extra == "all"
Dynamic: author
Dynamic: author-email
Dynamic: classifier
Dynamic: description
Dynamic: description-content-type
Dynamic: home-page
Dynamic: license-file
Dynamic: provides-extra
Dynamic: requires-dist
Dynamic: summary
